[
    {
        "path_id": 4,
        "name": "등산로입구",
        "lat": 35.757923,
        "lon": 127.086617
    },
    {
        "path_id": 5,
        "name": "온정식당 온정슈퍼",
        "lat": 35.757927,
        "lon": 127.086563
    },
    {
        "path_id": 6,
        "name": "충전소",
        "lat": 35.757885,
        "lon": 127.086319
    },
    {
        "path_id": 7,
        "name": "청하서원",
        "lat": 35.757462,
        "lon": 127.085411
    },
    {
        "path_id": 8,
        "name": "갈림길",
        "lat": 35.756874,
        "lon": 127.08506
    },
    {
        "path_id": 13,
        "name": "편백나무숲",
        "lat": 35.74725,
        "lon": 127.075783
    },
    {
        "path_id": 15,
        "name": "갈림길",
        "lat": 35.744179,
        "lon": 127.074234
    },
    {
        "path_id": 17,
        "name": "염불암",
        "lat": 35.742741,
        "lon": 127.072853
    },
    {
        "path_id": 18,
        "name": "식수",
        "lat": 35.742699,
        "lon": 127.072876
    },
    {
        "path_id": 21,
        "name": "갈림길",
        "lat": 35.739017,
        "lon": 127.074326
    },
    {
        "path_id": 25,
        "name": "국가지점번호",
        "lat": 35.732952,
        "lon": 127.081024
    },
    {
        "path_id": 27,
        "name": "싐터",
        "lat": 35.728947,
        "lon": 127.083328
    },
    {
        "path_id": 28,
        "name": "갈림길",
        "lat": 35.72855,
        "lon": 127.084785
    },
    {
        "path_id": 30,
        "name": "정상",
        "lat": 35.72858,
        "lon": 127.085114
    },
    {
        "path_id": 34,
        "name": "갈림길",
        "lat": 35.731281,
        "lon": 127.086571
    },
    {
        "path_id": 41,
        "name": "국가지점번호",
        "lat": 35.732349,
        "lon": 127.092262
    },
    {
        "path_id": 42,
        "name": "대원사",
        "lat": 35.731915,
        "lon": 127.095619
    },
    {
        "path_id": 44,
        "name": "국가지점번호",
        "lat": 35.731926,
        "lon": 127.095642
    },
    {
        "path_id": 45,
        "name": "갈림길",
        "lat": 35.731888,
        "lon": 127.098297
    },
    {
        "path_id": 51,
        "name": "선녀폭포",
        "lat": 35.729847,
        "lon": 127.103882
    },
    {
        "path_id": 52,
        "name": "모악쉼터",
        "lat": 35.729565,
        "lon": 127.10556
    },
    {
        "path_id": 53,
        "name": "먼지털이",
        "lat": 35.729652,
        "lon": 127.106079
    },
    {
        "path_id": 54,
        "name": "만남의광장",
        "lat": 35.729595,
        "lon": 127.106094
    },
    {
        "path_id": 55,
        "name": "해충기피제 분사기",
        "lat": 35.729595,
        "lon": 127.106194
    },
    {
        "path_id": 58,
        "name": "갈림길",
        "lat": 35.729507,
        "lon": 127.10759
    },
    {
        "path_id": 61,
        "name": "모악산 관리사무소",
        "lat": 35.729294,
        "lon": 127.10984
    },
    {
        "path_id": 62,
        "name": "버스정류장",
        "lat": 35.729294,
        "lon": 127.109947
    },
    {
        "path_id": 63,
        "name": "충전소",
        "lat": 35.729263,
        "lon": 127.110268
    }
]