[
  {
    "path": [
      {
        "lat": 36.879906,
        "lng": 128.13176
      },
      {
        "lat": 36.879902,
        "lng": 128.131744
      }
    ],
    "color": "#61c28f"
  },
  {
    "path": [
      {
        "lat": 36.879902,
        "lng": 128.131744
      },
      {
        "lat": 36.879929,
        "lng": 128.131714
      }
    ],
    "color": "#c3c9c8"
  },
  {
    "path": [
      {
        "lat": 36.879929,
        "lng": 128.131714
      },
      {
        "lat": 36.879925,
        "lng": 128.131714
      }
    ],
    "color": "#053689"
  },
  {
    "path": [
      {
        "lat": 36.879925,
        "lng": 128.131714
      },
      {
        "lat": 36.87994,
        "lng": 128.13179
      }
    ],
    "color": "#d51e04"
  },
  {
    "path": [
      {
        "lat": 36.87994,
        "lng": 128.13179
      },
      {
        "lat": 36.879971,
        "lng": 128.131729
      }
    ],
    "color": "#d23cbf"
  },
  {
    "path": [
      {
        "lat": 36.879971,
        "lng": 128.131729
      },
      {
        "lat": 36.879822,
        "lng": 128.131851
      }
    ],
    "color": "#d654ae"
  },
  {
    "path": [
      {
        "lat": 36.879822,
        "lng": 128.131851
      },
      {
        "lat": 36.879784,
        "lng": 128.131729
      }
    ],
    "color": "#911a06"
  },
  {
    "path": [
      {
        "lat": 36.879784,
        "lng": 128.131729
      },
      {
        "lat": 36.879482,
        "lng": 128.131332
      }
    ],
    "color": "#36461d"
  },
  {
    "path": [
      {
        "lat": 36.879482,
        "lng": 128.131332
      },
      {
        "lat": 36.879276,
        "lng": 128.131134
      }
    ],
    "color": "#c12114"
  },
  {
    "path": [
      {
        "lat": 36.879276,
        "lng": 128.131134
      },
      {
        "lat": 36.879196,
        "lng": 128.130707
      }
    ],
    "color": "#8b6f67"
  },
  {
    "path": [
      {
        "lat": 36.879196,
        "lng": 128.130707
      },
      {
        "lat": 36.879189,
        "lng": 128.13063
      }
    ],
    "color": "#4b5252"
  },
  {
    "path": [
      {
        "lat": 36.879189,
        "lng": 128.13063
      },
      {
        "lat": 36.879063,
        "lng": 128.130402
      }
    ],
    "color": "#1f94a4"
  },
  {
    "path": [
      {
        "lat": 36.879063,
        "lng": 128.130402
      },
      {
        "lat": 36.879063,
        "lng": 128.130402
      }
    ],
    "color": "#4cf18f"
  },
  {
    "path": [
      {
        "lat": 36.879063,
        "lng": 128.130402
      },
      {
        "lat": 36.879063,
        "lng": 128.130402
      }
    ],
    "color": "#fa6675"
  },
  {
    "path": [
      {
        "lat": 36.879063,
        "lng": 128.130402
      },
      {
        "lat": 36.879063,
        "lng": 128.130402
      }
    ],
    "color": "#e2e5a3"
  },
  {
    "path": [
      {
        "lat": 36.879063,
        "lng": 128.130402
      },
      {
        "lat": 36.879063,
        "lng": 128.130402
      }
    ],
    "color": "#164916"
  },
  {
    "path": [
      {
        "lat": 36.879063,
        "lng": 128.130402
      },
      {
        "lat": 36.879082,
        "lng": 128.130264
      }
    ],
    "color": "#daef20"
  },
  {
    "path": [
      {
        "lat": 36.879082,
        "lng": 128.130264
      },
      {
        "lat": 36.879181,
        "lng": 128.130264
      }
    ],
    "color": "#f3e6b0"
  },
  {
    "path": [
      {
        "lat": 36.879181,
        "lng": 128.130264
      },
      {
        "lat": 36.879223,
        "lng": 128.130249
      }
    ],
    "color": "#22fd58"
  },
  {
    "path": [
      {
        "lat": 36.879223,
        "lng": 128.130249
      },
      {
        "lat": 36.879181,
        "lng": 128.130264
      }
    ],
    "color": "#794756"
  },
  {
    "path": [
      {
        "lat": 36.879181,
        "lng": 128.130264
      },
      {
        "lat": 36.879181,
        "lng": 128.130264
      }
    ],
    "color": "#637140"
  },
  {
    "path": [
      {
        "lat": 36.879181,
        "lng": 128.130264
      },
      {
        "lat": 36.879318,
        "lng": 128.130188
      }
    ],
    "color": "#ff0989"
  },
  {
    "path": [
      {
        "lat": 36.879318,
        "lng": 128.130188
      },
      {
        "lat": 36.879402,
        "lng": 128.130188
      }
    ],
    "color": "#b33733"
  },
  {
    "path": [
      {
        "lat": 36.879402,
        "lng": 128.130188
      },
      {
        "lat": 36.879368,
        "lng": 128.130173
      }
    ],
    "color": "#a1e5aa"
  },
  {
    "path": [
      {
        "lat": 36.879368,
        "lng": 128.130173
      },
      {
        "lat": 36.879429,
        "lng": 128.130005
      }
    ],
    "color": "#52768d"
  },
  {
    "path": [
      {
        "lat": 36.879429,
        "lng": 128.130005
      },
      {
        "lat": 36.879284,
        "lng": 128.129868
      }
    ],
    "color": "#775ca5"
  },
  {
    "path": [
      {
        "lat": 36.879284,
        "lng": 128.129868
      },
      {
        "lat": 36.879238,
        "lng": 128.129868
      }
    ],
    "color": "#4429ee"
  },
  {
    "path": [
      {
        "lat": 36.879238,
        "lng": 128.129868
      },
      {
        "lat": 36.879173,
        "lng": 128.129898
      }
    ],
    "color": "#f8ed96"
  },
  {
    "path": [
      {
        "lat": 36.879173,
        "lng": 128.129898
      },
      {
        "lat": 36.878826,
        "lng": 128.13028
      }
    ],
    "color": "#8af007"
  },
  {
    "path": [
      {
        "lat": 36.878826,
        "lng": 128.13028
      },
      {
        "lat": 36.878891,
        "lng": 128.129745
      }
    ],
    "color": "#ae4a14"
  },
  {
    "path": [
      {
        "lat": 36.878891,
        "lng": 128.129745
      },
      {
        "lat": 36.879353,
        "lng": 128.126083
      }
    ],
    "color": "#d75dae"
  },
  {
    "path": [
      {
        "lat": 36.879353,
        "lng": 128.126083
      },
      {
        "lat": 36.879204,
        "lng": 128.124756
      }
    ],
    "color": "#24943b"
  },
  {
    "path": [
      {
        "lat": 36.879204,
        "lng": 128.124756
      },
      {
        "lat": 36.879074,
        "lng": 128.124573
      }
    ],
    "color": "#b33f5b"
  },
  {
    "path": [
      {
        "lat": 36.879074,
        "lng": 128.124573
      },
      {
        "lat": 36.878853,
        "lng": 128.124374
      }
    ],
    "color": "#a7be10"
  },
  {
    "path": [
      {
        "lat": 36.878853,
        "lng": 128.124374
      },
      {
        "lat": 36.878834,
        "lng": 128.124344
      }
    ],
    "color": "#d4e84d"
  },
  {
    "path": [
      {
        "lat": 36.878834,
        "lng": 128.124344
      },
      {
        "lat": 36.878765,
        "lng": 128.124283
      }
    ],
    "color": "#3a48df"
  },
  {
    "path": [
      {
        "lat": 36.878765,
        "lng": 128.124283
      },
      {
        "lat": 36.878685,
        "lng": 128.1241
      }
    ],
    "color": "#8c8b0c"
  },
  {
    "path": [
      {
        "lat": 36.878685,
        "lng": 128.1241
      },
      {
        "lat": 36.878632,
        "lng": 128.122833
      }
    ],
    "color": "#7c752d"
  },
  {
    "path": [
      {
        "lat": 36.878632,
        "lng": 128.122833
      },
      {
        "lat": 36.878826,
        "lng": 128.120468
      }
    ],
    "color": "#2dbbfb"
  },
  {
    "path": [
      {
        "lat": 36.878826,
        "lng": 128.120468
      },
      {
        "lat": 36.879368,
        "lng": 128.120026
      }
    ],
    "color": "#3aba17"
  },
  {
    "path": [
      {
        "lat": 36.879368,
        "lng": 128.120026
      },
      {
        "lat": 36.879318,
        "lng": 128.120026
      }
    ],
    "color": "#e93d24"
  },
  {
    "path": [
      {
        "lat": 36.879318,
        "lng": 128.120026
      },
      {
        "lat": 36.879368,
        "lng": 128.119812
      }
    ],
    "color": "#a098a8"
  },
  {
    "path": [
      {
        "lat": 36.879368,
        "lng": 128.119812
      },
      {
        "lat": 36.879684,
        "lng": 128.119431
      }
    ],
    "color": "#06b438"
  },
  {
    "path": [
      {
        "lat": 36.879684,
        "lng": 128.119431
      },
      {
        "lat": 36.879765,
        "lng": 128.119354
      }
    ],
    "color": "#bc2607"
  },
  {
    "path": [
      {
        "lat": 36.879765,
        "lng": 128.119354
      },
      {
        "lat": 36.880295,
        "lng": 128.118759
      }
    ],
    "color": "#bcdd04"
  },
  {
    "path": [
      {
        "lat": 36.880295,
        "lng": 128.118759
      },
      {
        "lat": 36.881649,
        "lng": 128.117111
      }
    ],
    "color": "#afab58"
  },
  {
    "path": [
      {
        "lat": 36.881649,
        "lng": 128.117111
      },
      {
        "lat": 36.881649,
        "lng": 128.117096
      }
    ],
    "color": "#849cd4"
  },
  {
    "path": [
      {
        "lat": 36.881649,
        "lng": 128.117096
      },
      {
        "lat": 36.881821,
        "lng": 128.116989
      }
    ],
    "color": "#4ffb2c"
  },
  {
    "path": [
      {
        "lat": 36.881821,
        "lng": 128.116989
      },
      {
        "lat": 36.881844,
        "lng": 128.116974
      }
    ],
    "color": "#e5500d"
  },
  {
    "path": [
      {
        "lat": 36.881844,
        "lng": 128.116974
      },
      {
        "lat": 36.882504,
        "lng": 128.116608
      }
    ],
    "color": "#5e49a0"
  },
  {
    "path": [
      {
        "lat": 36.882504,
        "lng": 128.116608
      },
      {
        "lat": 36.882557,
        "lng": 128.116592
      }
    ],
    "color": "#0910ef"
  },
  {
    "path": [
      {
        "lat": 36.882557,
        "lng": 128.116592
      },
      {
        "lat": 36.883224,
        "lng": 128.116348
      }
    ],
    "color": "#c7fba0"
  },
  {
    "path": [
      {
        "lat": 36.883224,
        "lng": 128.116348
      },
      {
        "lat": 36.883514,
        "lng": 128.116272
      }
    ],
    "color": "#c8eb6b"
  },
  {
    "path": [
      {
        "lat": 36.883514,
        "lng": 128.116272
      },
      {
        "lat": 36.883942,
        "lng": 128.116089
      }
    ],
    "color": "#ae3c36"
  },
  {
    "path": [
      {
        "lat": 36.883942,
        "lng": 128.116089
      },
      {
        "lat": 36.884403,
        "lng": 128.115967
      }
    ],
    "color": "#f9f062"
  },
  {
    "path": [
      {
        "lat": 36.884403,
        "lng": 128.115967
      },
      {
        "lat": 36.884495,
        "lng": 128.115921
      }
    ],
    "color": "#b08a11"
  },
  {
    "path": [
      {
        "lat": 36.884495,
        "lng": 128.115921
      },
      {
        "lat": 36.884541,
        "lng": 128.115875
      }
    ],
    "color": "#b8e982"
  },
  {
    "path": [
      {
        "lat": 36.884541,
        "lng": 128.115875
      },
      {
        "lat": 36.884552,
        "lng": 128.115875
      }
    ],
    "color": "#dcac58"
  },
  {
    "path": [
      {
        "lat": 36.884552,
        "lng": 128.115875
      },
      {
        "lat": 36.884468,
        "lng": 128.115387
      }
    ],
    "color": "#baaa25"
  },
  {
    "path": [
      {
        "lat": 36.884468,
        "lng": 128.115387
      },
      {
        "lat": 36.884434,
        "lng": 128.114914
      }
    ],
    "color": "#a43bd9"
  },
  {
    "path": [
      {
        "lat": 36.884434,
        "lng": 128.114914
      },
      {
        "lat": 36.88438,
        "lng": 128.11441
      }
    ],
    "color": "#fa8f43"
  },
  {
    "path": [
      {
        "lat": 36.88438,
        "lng": 128.11441
      },
      {
        "lat": 36.884338,
        "lng": 128.114075
      }
    ],
    "color": "#204c38"
  },
  {
    "path": [
      {
        "lat": 36.884338,
        "lng": 128.114075
      },
      {
        "lat": 36.885509,
        "lng": 128.112228
      }
    ],
    "color": "#48833e"
  },
  {
    "path": [
      {
        "lat": 36.885509,
        "lng": 128.112228
      },
      {
        "lat": 36.88554,
        "lng": 128.111588
      }
    ],
    "color": "#54e1d9"
  },
  {
    "path": [
      {
        "lat": 36.88554,
        "lng": 128.111588
      },
      {
        "lat": 36.885597,
        "lng": 128.111404
      }
    ],
    "color": "#a722eb"
  },
  {
    "path": [
      {
        "lat": 36.885597,
        "lng": 128.111404
      },
      {
        "lat": 36.885849,
        "lng": 128.110931
      }
    ],
    "color": "#9e8264"
  },
  {
    "path": [
      {
        "lat": 36.885849,
        "lng": 128.110931
      },
      {
        "lat": 36.885639,
        "lng": 128.110428
      }
    ],
    "color": "#70fffc"
  },
  {
    "path": [
      {
        "lat": 36.885639,
        "lng": 128.110428
      },
      {
        "lat": 36.885723,
        "lng": 128.110275
      }
    ],
    "color": "#a36a52"
  },
  {
    "path": [
      {
        "lat": 36.885723,
        "lng": 128.110275
      },
      {
        "lat": 36.886211,
        "lng": 128.109436
      }
    ],
    "color": "#d4a58c"
  },
  {
    "path": [
      {
        "lat": 36.886211,
        "lng": 128.109436
      },
      {
        "lat": 36.886208,
        "lng": 128.108826
      }
    ],
    "color": "#a57e77"
  },
  {
    "path": [
      {
        "lat": 36.886208,
        "lng": 128.108826
      },
      {
        "lat": 36.886181,
        "lng": 128.108749
      }
    ],
    "color": "#0f51f2"
  },
  {
    "path": [
      {
        "lat": 36.886181,
        "lng": 128.108749
      },
      {
        "lat": 36.886375,
        "lng": 128.108536
      }
    ],
    "color": "#a581f8"
  },
  {
    "path": [
      {
        "lat": 36.886375,
        "lng": 128.108536
      },
      {
        "lat": 36.886208,
        "lng": 128.109558
      }
    ],
    "color": "#1b23a3"
  },
  {
    "path": [
      {
        "lat": 36.886208,
        "lng": 128.109558
      },
      {
        "lat": 36.885941,
        "lng": 128.110077
      }
    ],
    "color": "#1be543"
  },
  {
    "path": [
      {
        "lat": 36.885941,
        "lng": 128.110077
      },
      {
        "lat": 36.885792,
        "lng": 128.110123
      }
    ],
    "color": "#d81ce1"
  },
  {
    "path": [
      {
        "lat": 36.885792,
        "lng": 128.110123
      },
      {
        "lat": 36.885853,
        "lng": 128.110886
      }
    ],
    "color": "#be03de"
  },
  {
    "path": [
      {
        "lat": 36.885853,
        "lng": 128.110886
      },
      {
        "lat": 36.885674,
        "lng": 128.111038
      }
    ],
    "color": "#0825a5"
  },
  {
    "path": [
      {
        "lat": 36.885674,
        "lng": 128.111038
      },
      {
        "lat": 36.885677,
        "lng": 128.111191
      }
    ],
    "color": "#f89ea9"
  },
  {
    "path": [
      {
        "lat": 36.885677,
        "lng": 128.111191
      },
      {
        "lat": 36.885002,
        "lng": 128.112701
      }
    ],
    "color": "#881b5c"
  },
  {
    "path": [
      {
        "lat": 36.885002,
        "lng": 128.112701
      },
      {
        "lat": 36.884342,
        "lng": 128.113785
      }
    ],
    "color": "#539f13"
  },
  {
    "path": [
      {
        "lat": 36.884342,
        "lng": 128.113785
      },
      {
        "lat": 36.884327,
        "lng": 128.113998
      }
    ],
    "color": "#9367d1"
  },
  {
    "path": [
      {
        "lat": 36.884327,
        "lng": 128.113998
      },
      {
        "lat": 36.884518,
        "lng": 128.115799
      }
    ],
    "color": "#c7d68a"
  },
  {
    "path": [
      {
        "lat": 36.884518,
        "lng": 128.115799
      },
      {
        "lat": 36.883812,
        "lng": 128.116043
      }
    ],
    "color": "#fff861"
  },
  {
    "path": [
      {
        "lat": 36.883812,
        "lng": 128.116043
      },
      {
        "lat": 36.883438,
        "lng": 128.116302
      }
    ],
    "color": "#204f16"
  },
  {
    "path": [
      {
        "lat": 36.883438,
        "lng": 128.116302
      },
      {
        "lat": 36.883411,
        "lng": 128.116241
      }
    ],
    "color": "#dba885"
  },
  {
    "path": [
      {
        "lat": 36.883411,
        "lng": 128.116241
      },
      {
        "lat": 36.883057,
        "lng": 128.116348
      }
    ],
    "color": "#beba81"
  },
  {
    "path": [
      {
        "lat": 36.883057,
        "lng": 128.116348
      },
      {
        "lat": 36.882778,
        "lng": 128.116501
      }
    ],
    "color": "#02eebe"
  },
  {
    "path": [
      {
        "lat": 36.882778,
        "lng": 128.116501
      },
      {
        "lat": 36.879646,
        "lng": 128.119507
      }
    ],
    "color": "#0f09db"
  },
  {
    "path": [
      {
        "lat": 36.879646,
        "lng": 128.119507
      },
      {
        "lat": 36.879009,
        "lng": 128.120148
      }
    ],
    "color": "#6d2998"
  },
  {
    "path": [
      {
        "lat": 36.879009,
        "lng": 128.120148
      },
      {
        "lat": 36.878971,
        "lng": 128.120331
      }
    ],
    "color": "#7e925e"
  },
  {
    "path": [
      {
        "lat": 36.878971,
        "lng": 128.120331
      },
      {
        "lat": 36.878819,
        "lng": 128.120712
      }
    ],
    "color": "#f2354b"
  },
  {
    "path": [
      {
        "lat": 36.878819,
        "lng": 128.120712
      },
      {
        "lat": 36.878609,
        "lng": 128.121353
      }
    ],
    "color": "#50791c"
  },
  {
    "path": [
      {
        "lat": 36.878609,
        "lng": 128.121353
      },
      {
        "lat": 36.878651,
        "lng": 128.12175
      }
    ],
    "color": "#11cc01"
  },
  {
    "path": [
      {
        "lat": 36.878651,
        "lng": 128.12175
      },
      {
        "lat": 36.878716,
        "lng": 128.123169
      }
    ],
    "color": "#4b08af"
  },
  {
    "path": [
      {
        "lat": 36.878716,
        "lng": 128.123169
      },
      {
        "lat": 36.878731,
        "lng": 128.123398
      }
    ],
    "color": "#626d09"
  },
  {
    "path": [
      {
        "lat": 36.878731,
        "lng": 128.123398
      },
      {
        "lat": 36.878677,
        "lng": 128.124039
      }
    ],
    "color": "#8ea1f3"
  },
  {
    "path": [
      {
        "lat": 36.878677,
        "lng": 128.124039
      },
      {
        "lat": 36.879066,
        "lng": 128.124634
      }
    ],
    "color": "#0da881"
  },
  {
    "path": [
      {
        "lat": 36.879066,
        "lng": 128.124634
      },
      {
        "lat": 36.879196,
        "lng": 128.129272
      }
    ],
    "color": "#55a021"
  },
  {
    "path": [
      {
        "lat": 36.879196,
        "lng": 128.129272
      },
      {
        "lat": 36.878918,
        "lng": 128.129776
      }
    ],
    "color": "#7a3438"
  },
  {
    "path": [
      {
        "lat": 36.878918,
        "lng": 128.129776
      },
      {
        "lat": 36.878857,
        "lng": 128.130157
      }
    ],
    "color": "#41cf69"
  },
  {
    "path": [
      {
        "lat": 36.878857,
        "lng": 128.130157
      },
      {
        "lat": 36.879017,
        "lng": 128.130264
      }
    ],
    "color": "#259fc9"
  },
  {
    "path": [
      {
        "lat": 36.879017,
        "lng": 128.130264
      },
      {
        "lat": 36.878983,
        "lng": 128.130081
      }
    ],
    "color": "#cb1d2b"
  },
  {
    "path": [
      {
        "lat": 36.878983,
        "lng": 128.130081
      },
      {
        "lat": 36.879066,
        "lng": 128.130234
      }
    ],
    "color": "#d902d2"
  },
  {
    "path": [
      {
        "lat": 36.879066,
        "lng": 128.130234
      },
      {
        "lat": 36.879131,
        "lng": 128.13031
      }
    ],
    "color": "#52c25e"
  },
  {
    "path": [
      {
        "lat": 36.879131,
        "lng": 128.13031
      },
      {
        "lat": 36.879227,
        "lng": 128.130905
      }
    ],
    "color": "#d011cb"
  },
  {
    "path": [
      {
        "lat": 36.879227,
        "lng": 128.130905
      },
      {
        "lat": 36.879818,
        "lng": 128.131683
      }
    ],
    "color": "#1d4735"
  },
  {
    "path": [
      {
        "lat": 36.879818,
        "lng": 128.131683
      },
      {
        "lat": 36.879913,
        "lng": 128.131805
      }
    ],
    "color": "#869e50"
  }
]