[
  {
    "path_id": 0,
    "path": [
      {
        "lat": 35.464317,
        "lng": 126.837601
      },
      {
        "lat": 35.463593,
        "lng": 126.837334
      }
    ],
    "color": "#3b2e68",
    "start_name": "새재 화장실 / 무장애 탐방로 / 자연관찰로",
    "length_meter": 108.8,
    "time_minute": 1
  },
  {
    "path_id": 1,
    "path": [
      {
        "lat": 35.463593,
        "lng": 126.837334
      },
      {
        "lat": 35.462955,
        "lng": 126.83812
      }
    ],
    "color": "#2c6c91",
    "start_name": "남창골 가마터 / 너덜지대 지형 / 그네 쉼터",
    "length_meter": 102.9,
    "time_minute": 1
  },
  {
    "path_id": 2,
    "path": [
      {
        "lat": 35.462955,
        "lng": 126.83812
      },
      {
        "lat": 35.462776,
        "lng": 126.838791
      }
    ],
    "color": "#1e9440",
    "start_name": "낙엽분해관찰 / 남창골 새 이야기 / 간이쉼터 / 간이쉼터",
    "length_meter": 83.8,
    "time_minute": 1
  },
  {
    "path_id": 3,
    "path": [
      {
        "lat": 35.462776,
        "lng": 126.838791
      },
      {
        "lat": 35.463741,
        "lng": 126.838272
      }
    ],
    "color": "#fb124e",
    "start_name": "남창계곡 / 간이쉼터",
    "length_meter": 125.3,
    "time_minute": 2
  },
  {
    "path_id": 4,
    "path": [
      {
        "lat": 35.463741,
        "lng": 126.838272
      },
      {
        "lat": 35.465112,
        "lng": 126.836134
      }
    ],
    "color": "#306969",
    "start_name": "바위글씨와 일제시대 아픈 역사 이야기",
    "length_meter": 246.4,
    "time_minute": 4
  },
  {
    "path_id": 5,
    "path": [
      {
        "lat": 35.465112,
        "lng": 126.836134
      },
      {
        "lat": 35.478726,
        "lng": 126.841195
      }
    ],
    "color": "#8ebf69",
    "start_name": "전남대 장성학술팀 조림 현황 안내 / 갈림길 / 장성새재",
    "length_meter": 1590.9,
    "time_minute": 26
  },
  {
    "path_id": 6,
    "path": [
      {
        "lat": 35.478726,
        "lng": 126.841195
      },
      {
        "lat": 35.479706,
        "lng": 126.841058
      }
    ],
    "color": "#3a7682",
    "start_name": "위치번호 백암19-04 / 장성새재 오솔길",
    "length_meter": 110.4,
    "time_minute": 1
  },
  {
    "path_id": 7,
    "path": [
      {
        "lat": 35.479706,
        "lng": 126.841058
      },
      {
        "lat": 35.480759,
        "lng": 126.841339
      }
    ],
    "color": "#ba2a45",
    "start_name": "월은치",
    "length_meter": 119.8,
    "time_minute": 1
  },
  {
    "path_id": 8,
    "path": [
      {
        "lat": 35.480759,
        "lng": 126.841339
      },
      {
        "lat": 35.479709,
        "lng": 126.848452
      }
    ],
    "color": "#d4a352",
    "start_name": "장성새재  쉼터 / 갈림길",
    "length_meter": 655.5,
    "time_minute": 10
  },
  {
    "path_id": 9,
    "path": [
      {
        "lat": 35.479709,
        "lng": 126.848452
      },
      {
        "lat": 35.480165,
        "lng": 126.850164
      }
    ],
    "color": "#712b61",
    "start_name": "위치번호 내장10-03",
    "length_meter": 163.1,
    "time_minute": 2
  },
  {
    "path_id": 10,
    "path": [
      {
        "lat": 35.480165,
        "lng": 126.850164
      },
      {
        "lat": 35.479037,
        "lng": 126.852832
      }
    ],
    "color": "#d081ee",
    "start_name": "길 안내표지 / 순창새재 농가 / 순창새재 탐방로 안내표지판",
    "length_meter": 272.7,
    "time_minute": 4
  },
  {
    "path_id": 11,
    "path": [
      {
        "lat": 35.479037,
        "lng": 126.852832
      },
      {
        "lat": 35.478196,
        "lng": 126.855585
      }
    ],
    "color": "#7eab8a",
    "start_name": "길 안내표지",
    "length_meter": 266.2,
    "time_minute": 4
  },
  {
    "path_id": 12,
    "path": [
      {
        "lat": 35.478196,
        "lng": 126.855585
      },
      {
        "lat": 35.477734,
        "lng": 126.860901
      }
    ],
    "color": "#8917f4",
    "start_name": "위치번호 내장10-01",
    "length_meter": 484.1,
    "time_minute": 8
  },
  {
    "path_id": 13,
    "path": [
      {
        "lat": 35.477734,
        "lng": 126.860901
      },
      {
        "lat": 35.480006,
        "lng": 126.849795
      }
    ],
    "color": "#58d84d",
    "start_name": "갈림길 / 순창새재 / 산불진화장비 보관함",
    "length_meter": 1050.6,
    "time_minute": 17
  },
  {
    "path_id": 14,
    "path": [
      {
        "lat": 35.480006,
        "lng": 126.849795
      },
      {
        "lat": 35.488693,
        "lng": 126.840309
      }
    ],
    "color": "#378893",
    "start_name": "야생화",
    "length_meter": 1292.6,
    "time_minute": 21
  },
  {
    "path_id": 15,
    "path": [
      {
        "lat": 35.488693,
        "lng": 126.840309
      },
      {
        "lat": 35.491187,
        "lng": 126.841468
      }
    ],
    "color": "#9d3a84",
    "start_name": "위치번호 내장10-06",
    "length_meter": 296.5,
    "time_minute": 4
  },
  {
    "path_id": 16,
    "path": [
      {
        "lat": 35.491187,
        "lng": 126.841468
      },
      {
        "lat": 35.493176,
        "lng": 126.84111
      }
    ],
    "color": "#c2770c",
    "start_name": "장성새재 옛길",
    "length_meter": 223.5,
    "time_minute": 3
  },
  {
    "path_id": 17,
    "path": [
      {
        "lat": 35.493176,
        "lng": 126.84111
      },
      {
        "lat": 35.496754,
        "lng": 126.841637
      }
    ],
    "color": "#d4b9f8",
    "start_name": "위치번호 10-07",
    "length_meter": 400.7,
    "time_minute": 6
  },
  {
    "path_id": 18,
    "path": [
      {
        "lat": 35.496754,
        "lng": 126.841637
      },
      {
        "lat": 35.472843,
        "lng": 126.841454
      }
    ],
    "color": "#b854d3",
    "start_name": "입암공원지킴터 / 입암분소 / 입암공원 지킴터 탐방로 / 위치번호 안내판",
    "length_meter": 2680.1,
    "time_minute": 44
  },
  {
    "path_id": 19,
    "path": [
      {
        "lat": 35.472843,
        "lng": 126.841454
      },
      {
        "lat": 35.460835,
        "lng": 126.840881
      }
    ],
    "color": "#76d9dc",
    "start_name": "내장산 단풍",
    "length_meter": 1336.2,
    "time_minute": 22
  }
]