{
  "max_ele": 1359.866,
  "total_length_km": "7.4km",
  "total_time": "1시간 32분",
  "start_name": "영월공영 행복버스",
  "end_name": "웨이포인트 1",
  "track": [
    {
      "path_id": 0,
      "path": [
        {
          "lat": 37.38179,
          "lng": 128.270859
        },
        {
          "lat": 37.382919,
          "lng": 128.270416
        }
      ],
      "color": "#9f8209",
      "start_name": "영월공영 행복버스 / 간이화장실",
      "length_meter": 132.1,
      "time_minute": 2
    },
    {
      "path_id": 1,
      "path": [
        {
          "lat": 37.382919,
          "lng": 128.270416
        },
        {
          "lat": 37.389198,
          "lng": 128.270813
        }
      ],
      "color": "#bfb207",
      "start_name": "흥원사 / 백덕산등산로 입구, 흥원사",
      "length_meter": 749.1,
      "time_minute": 12
    },
    {
      "path_id": 2,
      "path": [
        {
          "lat": 37.389198,
          "lng": 128.270813
        },
        {
          "lat": 37.390495,
          "lng": 128.271454
        }
      ],
      "color": "#1b9121",
      "start_name": "설통바위",
      "length_meter": 154.9,
      "time_minute": 1
    },
    {
      "path_id": 3,
      "path": [
        {
          "lat": 37.390495,
          "lng": 128.271454
        },
        {
          "lat": 37.390942,
          "lng": 128.272949
        }
      ],
      "color": "#b39c88",
      "start_name": "갈림길",
      "length_meter": 141.1,
      "time_minute": 1
    },
    {
      "path_id": 4,
      "path": [
        {
          "lat": 37.390942,
          "lng": 128.272949
        },
        {
          "lat": 37.394619,
          "lng": 128.278412
        }
      ],
      "color": "#bf90c7",
      "start_name": "재단터",
      "length_meter": 632.5,
      "time_minute": 7
    },
    {
      "path_id": 5,
      "path": [
        {
          "lat": 37.394619,
          "lng": 128.278412
        },
        {
          "lat": 37.397178,
          "lng": 128.282506
        }
      ],
      "color": "#baad02",
      "start_name": "전망대 / 웨이포인트 9",
      "length_meter": 462.2,
      "time_minute": 7
    },
    {
      "path_id": 6,
      "path": [
        {
          "lat": 37.397178,
          "lng": 128.282506
        },
        {
          "lat": 37.397091,
          "lng": 128.283599
        }
      ],
      "color": "#85681f",
      "start_name": "웨이포인트 10",
      "length_meter": 97.0,
      "time_minute": 1
    },
    {
      "path_id": 7,
      "path": [
        {
          "lat": 37.397091,
          "lng": 128.283599
        },
        {
          "lat": 37.396992,
          "lng": 128.285797
        }
      ],
      "color": "#80b798",
      "start_name": "웨이포인트 11",
      "length_meter": 194.5,
      "time_minute": 2
    },
    {
      "path_id": 8,
      "path": [
        {
          "lat": 37.396992,
          "lng": 128.285797
        },
        {
          "lat": 37.397186,
          "lng": 128.291504
        }
      ],
      "color": "#c26da8",
      "start_name": "낙타바위 전망대",
      "length_meter": 504.6,
      "time_minute": 6
    },
    {
      "path_id": 9,
      "path": [
        {
          "lat": 37.397186,
          "lng": 128.291504
        },
        {
          "lat": 37.396717,
          "lng": 128.291611
        }
      ],
      "color": "#735d2d",
      "start_name": "용바위",
      "length_meter": 53.0,
      "time_minute": 0
    },
    {
      "path_id": 10,
      "path": [
        {
          "lat": 37.396717,
          "lng": 128.291611
        },
        {
          "lat": 37.396553,
          "lng": 128.29332
        }
      ],
      "color": "#c08714",
      "start_name": "백덕산정상  가기 전 바위",
      "length_meter": 152.1,
      "time_minute": 1
    },
    {
      "path_id": 11,
      "path": [
        {
          "lat": 37.396553,
          "lng": 128.29332
        },
        {
          "lat": 37.394449,
          "lng": 128.294478
        }
      ],
      "color": "#999d89",
      "start_name": "갈림길 / 백덕산정상",
      "length_meter": 257.3,
      "time_minute": 4
    },
    {
      "path_id": 12,
      "path": [
        {
          "lat": 37.394449,
          "lng": 128.294478
        },
        {
          "lat": 37.389374,
          "lng": 128.297348
        }
      ],
      "color": "#555966",
      "start_name": "웨이포인트 18",
      "length_meter": 618.7,
      "time_minute": 7
    },
    {
      "path_id": 13,
      "path": [
        {
          "lat": 37.389374,
          "lng": 128.297348
        },
        {
          "lat": 37.389271,
          "lng": 128.298004
        }
      ],
      "color": "#270467",
      "start_name": "갈림길 / 웨이포인트 20",
      "length_meter": 59.1,
      "time_minute": 0
    },
    {
      "path_id": 14,
      "path": [
        {
          "lat": 37.389271,
          "lng": 128.298004
        },
        {
          "lat": 37.388203,
          "lng": 128.297043
        }
      ],
      "color": "#3ec4aa",
      "start_name": "부부바위전망대",
      "length_meter": 146.0,
      "time_minute": 1
    },
    {
      "path_id": 15,
      "path": [
        {
          "lat": 37.388203,
          "lng": 128.297043
        },
        {
          "lat": 37.387161,
          "lng": 128.296616
        }
      ],
      "color": "#2d24b6",
      "start_name": "갈림길 / 촛대바위",
      "length_meter": 123.2,
      "time_minute": 2
    },
    {
      "path_id": 16,
      "path": [
        {
          "lat": 37.387161,
          "lng": 128.296616
        },
        {
          "lat": 37.381641,
          "lng": 128.295441
        }
      ],
      "color": "#162c40",
      "start_name": "급경사",
      "length_meter": 622.5,
      "time_minute": 7
    },
    {
      "path_id": 17,
      "path": [
        {
          "lat": 37.381641,
          "lng": 128.295441
        },
        {
          "lat": 37.381004,
          "lng": 128.294861
        }
      ],
      "color": "#386636",
      "start_name": "갈림길 / 신선바위가기전 전망대 / 웨이포인트 27 / 위험구간",
      "length_meter": 97.7,
      "time_minute": 1
    },
    {
      "path_id": 18,
      "path": [
        {
          "lat": 37.381004,
          "lng": 128.294861
        },
        {
          "lat": 37.380932,
          "lng": 128.294818
        }
      ],
      "color": "#734b63",
      "start_name": "신선바위",
      "length_meter": 8.9,
      "time_minute": 0
    },
    {
      "path_id": 19,
      "path": [
        {
          "lat": 37.380932,
          "lng": 128.294818
        },
        {
          "lat": 37.380817,
          "lng": 128.281433
        }
      ],
      "color": "#64243f",
      "start_name": "웨이포인트 30 / 갈림길 / 웨이포인트 32",
      "length_meter": 1228.8,
      "time_minute": 20
    },
    {
      "path_id": 20,
      "path": [
        {
          "lat": 37.380817,
          "lng": 128.281433
        },
        {
          "lat": 37.382191,
          "lng": 128.271088
        }
      ],
      "color": "#2b7952",
      "start_name": "흥원사 대략 1Km전",
      "length_meter": 926.7,
      "time_minute": 11
    },
    {
      "path_id": 21,
      "path": [
        {
          "lat": 37.382191,
          "lng": 128.271088
        },
        {
          "lat": 37.382029,
          "lng": 128.270746
        }
      ],
      "color": "#35b227",
      "start_name": "갈림길 / 백덕산등산로입구, 백년계곡",
      "length_meter": 40.1,
      "time_minute": 0
    }
  ]
}