[
  {
    "path": [
      {
        "lat": 37.457699,
        "lng": 129.004074
      },
      {
        "lat": 37.452553,
        "lng": 129.006851
      }
    ],
    "color": "#ac9b2f"
  },
  {
    "path": [
      {
        "lat": 37.452553,
        "lng": 129.006851
      },
      {
        "lat": 37.45216,
        "lng": 129.007004
      }
    ],
    "color": "#42fdce"
  },
  {
    "path": [
      {
        "lat": 37.45216,
        "lng": 129.007004
      },
      {
        "lat": 37.439888,
        "lng": 129.007751
      }
    ],
    "color": "#a9ceac"
  },
  {
    "path": [
      {
        "lat": 37.439888,
        "lng": 129.007751
      },
      {
        "lat": 37.434914,
        "lng": 129.008713
      }
    ],
    "color": "#d50cba"
  },
  {
    "path": [
      {
        "lat": 37.434914,
        "lng": 129.008713
      },
      {
        "lat": 37.434357,
        "lng": 129.008682
      }
    ],
    "color": "#532498"
  },
  {
    "path": [
      {
        "lat": 37.434357,
        "lng": 129.008682
      },
      {
        "lat": 37.434315,
        "lng": 129.008682
      }
    ],
    "color": "#6d7db3"
  },
  {
    "path": [
      {
        "lat": 37.434315,
        "lng": 129.008682
      },
      {
        "lat": 37.430813,
        "lng": 129.007675
      }
    ],
    "color": "#017f1d"
  },
  {
    "path": [
      {
        "lat": 37.430813,
        "lng": 129.007675
      },
      {
        "lat": 37.430782,
        "lng": 129.00766
      }
    ],
    "color": "#05966a"
  },
  {
    "path": [
      {
        "lat": 37.430782,
        "lng": 129.00766
      },
      {
        "lat": 37.42664,
        "lng": 129.0047
      }
    ],
    "color": "#766064"
  },
  {
    "path": [
      {
        "lat": 37.42664,
        "lng": 129.0047
      },
      {
        "lat": 37.42905,
        "lng": 129.001068
      }
    ],
    "color": "#e8fb83"
  },
  {
    "path": [
      {
        "lat": 37.42905,
        "lng": 129.001068
      },
      {
        "lat": 37.431248,
        "lng": 128.992371
      }
    ],
    "color": "#80d86c"
  },
  {
    "path": [
      {
        "lat": 37.431248,
        "lng": 128.992371
      },
      {
        "lat": 37.433926,
        "lng": 128.984573
      }
    ],
    "color": "#855a7d"
  },
  {
    "path": [
      {
        "lat": 37.433926,
        "lng": 128.984573
      },
      {
        "lat": 37.434006,
        "lng": 128.984436
      }
    ],
    "color": "#84e70f"
  },
  {
    "path": [
      {
        "lat": 37.434006,
        "lng": 128.984436
      },
      {
        "lat": 37.434422,
        "lng": 128.97345
      }
    ],
    "color": "#5266d2"
  },
  {
    "path": [
      {
        "lat": 37.434422,
        "lng": 128.97345
      },
      {
        "lat": 37.435181,
        "lng": 128.974487
      }
    ],
    "color": "#c97313"
  },
  {
    "path": [
      {
        "lat": 37.435181,
        "lng": 128.974487
      },
      {
        "lat": 37.45208,
        "lng": 128.994705
      }
    ],
    "color": "#a19b74"
  },
  {
    "path": [
      {
        "lat": 37.45208,
        "lng": 128.994705
      },
      {
        "lat": 37.452759,
        "lng": 128.991867
      }
    ],
    "color": "#4d3ddc"
  },
  {
    "path": [
      {
        "lat": 37.452759,
        "lng": 128.991867
      },
      {
        "lat": 37.453548,
        "lng": 128.99263
      }
    ],
    "color": "#bf7ef5"
  },
  {
    "path": [
      {
        "lat": 37.453548,
        "lng": 128.99263
      },
      {
        "lat": 37.454403,
        "lng": 128.995819
      }
    ],
    "color": "#191f82"
  },
  {
    "path": [
      {
        "lat": 37.454403,
        "lng": 128.995819
      },
      {
        "lat": 37.455269,
        "lng": 128.997604
      }
    ],
    "color": "#77de85"
  },
  {
    "path": [
      {
        "lat": 37.455269,
        "lng": 128.997604
      },
      {
        "lat": 37.45528,
        "lng": 128.997574
      }
    ],
    "color": "#ed3ae1"
  },
  {
    "path": [
      {
        "lat": 37.45528,
        "lng": 128.997574
      },
      {
        "lat": 37.454441,
        "lng": 128.998199
      }
    ],
    "color": "#4bcd55"
  },
  {
    "path": [
      {
        "lat": 37.454441,
        "lng": 128.998199
      },
      {
        "lat": 37.454414,
        "lng": 128.998367
      }
    ],
    "color": "#c2ca99"
  },
  {
    "path": [
      {
        "lat": 37.454414,
        "lng": 128.998367
      },
      {
        "lat": 37.456646,
        "lng": 129.000931
      }
    ],
    "color": "#85f283"
  },
  {
    "path": [
      {
        "lat": 37.456646,
        "lng": 129.000931
      },
      {
        "lat": 37.456718,
        "lng": 129.000992
      }
    ],
    "color": "#4ad6d6"
  },
  {
    "path": [
      {
        "lat": 37.456718,
        "lng": 129.000992
      },
      {
        "lat": 37.457714,
        "lng": 129.004105
      }
    ],
    "color": "#8eaf0a"
  }
]