[
  {
    "path_id": 0,
    "path": [
      {
        "lat": 37.457699,
        "lng": 129.004074
      },
      {
        "lat": 37.452553,
        "lng": 129.006851
      }
    ],
    "color": "#9f3313",
    "start_point_name": "국가지점번호",
    "length": 622,
    "time": "10"
  },
  {
    "path_id": 1,
    "path": [
      {
        "lat": 37.452553,
        "lng": 129.006851
      },
      {
        "lat": 37.45216,
        "lng": 129.007004
      }
    ],
    "color": "#8c87b6",
    "start_point_name": "갈림길",
    "length": 45,
    "time": "0"
  },
  {
    "path_id": 2,
    "path": [
      {
        "lat": 37.45216,
        "lng": 129.007004
      },
      {
        "lat": 37.439888,
        "lng": 129.007751
      }
    ],
    "color": "#45a0ea",
    "start_point_name": "갈림길",
    "length": 1366,
    "time": "22"
  },
  {
    "path_id": 3,
    "path": [
      {
        "lat": 37.439888,
        "lng": 129.007751
      },
      {
        "lat": 37.434914,
        "lng": 129.008713
      }
    ],
    "color": "#0e464e",
    "start_point_name": "갈림길",
    "length": 559,
    "time": "9"
  },
  {
    "path_id": 4,
    "path": [
      {
        "lat": 37.434914,
        "lng": 129.008713
      },
      {
        "lat": 37.434357,
        "lng": 129.008682
      }
    ],
    "color": "#1eff71",
    "start_point_name": "조망점",
    "length": 61,
    "time": "1"
  },
  {
    "path_id": 5,
    "path": [
      {
        "lat": 37.434357,
        "lng": 129.008682
      },
      {
        "lat": 37.434315,
        "lng": 129.008682
      }
    ],
    "color": "#be6211",
    "start_point_name": "갈림길",
    "length": 4,
    "time": "0"
  },
  {
    "path_id": 6,
    "path": [
      {
        "lat": 37.434315,
        "lng": 129.008682
      },
      {
        "lat": 37.430813,
        "lng": 129.007675
      }
    ],
    "color": "#aaff36",
    "start_point_name": "국가지점번호",
    "length": 399,
    "time": "6"
  },
  {
    "path_id": 7,
    "path": [
      {
        "lat": 37.430813,
        "lng": 129.007675
      },
      {
        "lat": 37.430782,
        "lng": 129.00766
      }
    ],
    "color": "#7430c7",
    "start_point_name": "갈림길",
    "length": 3,
    "time": "0"
  },
  {
    "path_id": 8,
    "path": [
      {
        "lat": 37.430782,
        "lng": 129.00766
      },
      {
        "lat": 37.42664,
        "lng": 129.0047
      }
    ],
    "color": "#de3492",
    "start_point_name": "국가지점번호",
    "length": 529,
    "time": "8"
  },
  {
    "path_id": 9,
    "path": [
      {
        "lat": 37.42664,
        "lng": 129.0047
      },
      {
        "lat": 37.42905,
        "lng": 129.001068
      }
    ],
    "color": "#a3ad34",
    "start_point_name": "헬기장",
    "length": 417,
    "time": "6"
  },
  {
    "path_id": 10,
    "path": [
      {
        "lat": 37.42905,
        "lng": 129.001068
      },
      {
        "lat": 37.431248,
        "lng": 128.992371
      }
    ],
    "color": "#b02314",
    "start_point_name": "조망점",
    "length": 805,
    "time": "13"
  },
  {
    "path_id": 11,
    "path": [
      {
        "lat": 37.431248,
        "lng": 128.992371
      },
      {
        "lat": 37.433926,
        "lng": 128.984573
      }
    ],
    "color": "#9bb48c",
    "start_point_name": "조망점",
    "length": 750,
    "time": "12"
  },
  {
    "path_id": 12,
    "path": [
      {
        "lat": 37.433926,
        "lng": 128.984573
      },
      {
        "lat": 37.434006,
        "lng": 128.984436
      }
    ],
    "color": "#de3f18",
    "start_point_name": "갈림길",
    "length": 15,
    "time": "0"
  },
  {
    "path_id": 13,
    "path": [
      {
        "lat": 37.434006,
        "lng": 128.984436
      },
      {
        "lat": 37.434422,
        "lng": 128.97345
      }
    ],
    "color": "#a125b2",
    "start_point_name": "하천범람코스",
    "length": 971,
    "time": "16"
  },
  {
    "path_id": 14,
    "path": [
      {
        "lat": 37.434422,
        "lng": 128.97345
      },
      {
        "lat": 37.435181,
        "lng": 128.974487
      }
    ],
    "color": "#fdff69",
    "start_point_name": "갈림길",
    "length": 124,
    "time": "2"
  },
  {
    "path_id": 15,
    "path": [
      {
        "lat": 37.435181,
        "lng": 128.974487
      },
      {
        "lat": 37.45208,
        "lng": 128.994705
      }
    ],
    "color": "#cd8668",
    "start_point_name": "보호수목",
    "length": 2591,
    "time": "43"
  },
  {
    "path_id": 16,
    "path": [
      {
        "lat": 37.45208,
        "lng": 128.994705
      },
      {
        "lat": 37.452759,
        "lng": 128.991867
      }
    ],
    "color": "#49e1af",
    "start_point_name": "포토존",
    "length": 261,
    "time": "4"
  },
  {
    "path_id": 17,
    "path": [
      {
        "lat": 37.452759,
        "lng": 128.991867
      },
      {
        "lat": 37.453548,
        "lng": 128.99263
      }
    ],
    "color": "#8941b1",
    "start_point_name": "갈림길",
    "length": 110,
    "time": "1"
  },
  {
    "path_id": 18,
    "path": [
      {
        "lat": 37.453548,
        "lng": 128.99263
      },
      {
        "lat": 37.454403,
        "lng": 128.995819
      }
    ],
    "color": "#3c8f4f",
    "start_point_name": "절벽",
    "length": 297,
    "time": "4"
  },
  {
    "path_id": 19,
    "path": [
      {
        "lat": 37.454403,
        "lng": 128.995819
      },
      {
        "lat": 37.455269,
        "lng": 128.997604
      }
    ],
    "color": "#3bb1fe",
    "start_point_name": "갈림길",
    "length": 184,
    "time": "3"
  },
  {
    "path_id": 20,
    "path": [
      {
        "lat": 37.455269,
        "lng": 128.997604
      },
      {
        "lat": 37.45528,
        "lng": 128.997574
      }
    ],
    "color": "#21e99c",
    "start_point_name": "간이휴게소",
    "length": 2,
    "time": "0"
  },
  {
    "path_id": 21,
    "path": [
      {
        "lat": 37.45528,
        "lng": 128.997574
      },
      {
        "lat": 37.454441,
        "lng": 128.998199
      }
    ],
    "color": "#02d445",
    "start_point_name": "무릉계곡명승지안내도",
    "length": 108,
    "time": "1"
  },
  {
    "path_id": 22,
    "path": [
      {
        "lat": 37.454441,
        "lng": 128.998199
      },
      {
        "lat": 37.454414,
        "lng": 128.998367
      }
    ],
    "color": "#f8b26a",
    "start_point_name": "장군바위",
    "length": 15,
    "time": "0"
  },
  {
    "path_id": 23,
    "path": [
      {
        "lat": 37.454414,
        "lng": 128.998367
      },
      {
        "lat": 37.456646,
        "lng": 129.000931
      }
    ],
    "color": "#c6eb21",
    "start_point_name": "갈림길",
    "length": 335,
    "time": "5"
  },
  {
    "path_id": 24,
    "path": [
      {
        "lat": 37.456646,
        "lng": 129.000931
      },
      {
        "lat": 37.456718,
        "lng": 129.000992
      }
    ],
    "color": "#7733a6",
    "start_point_name": "얼레지쉼터",
    "length": 9,
    "time": "0"
  },
  {
    "path_id": 25,
    "path": [
      {
        "lat": 37.456718,
        "lng": 129.000992
      },
      {
        "lat": 37.457714,
        "lng": 129.004105
      }
    ],
    "color": "#8ab7c5",
    "start_point_name": "국가지점번호",
    "length": 296,
    "time": "4"
  }
]