[
  {
    "path": [
      {
        "lat": 37.081387,
        "lng": 129.279404
      },
      {
        "lat": 37.081528,
        "lng": 129.279587
      }
    ],
    "color": "#b2f18a"
  },
  {
    "path": [
      {
        "lat": 37.081528,
        "lng": 129.279587
      },
      {
        "lat": 37.081436,
        "lng": 129.279404
      }
    ],
    "color": "#05ae83"
  },
  {
    "path": [
      {
        "lat": 37.081436,
        "lng": 129.279404
      },
      {
        "lat": 37.08252,
        "lng": 129.272171
      }
    ],
    "color": "#f0d4d5"
  },
  {
    "path": [
      {
        "lat": 37.08252,
        "lng": 129.272171
      },
      {
        "lat": 37.082226,
        "lng": 129.267151
      }
    ],
    "color": "#2be78e"
  },
  {
    "path": [
      {
        "lat": 37.082226,
        "lng": 129.267151
      },
      {
        "lat": 37.081005,
        "lng": 129.256729
      }
    ],
    "color": "#566405"
  },
  {
    "path": [
      {
        "lat": 37.081005,
        "lng": 129.256729
      },
      {
        "lat": 37.079956,
        "lng": 129.255157
      }
    ],
    "color": "#feb657"
  },
  {
    "path": [
      {
        "lat": 37.079956,
        "lng": 129.255157
      },
      {
        "lat": 37.079266,
        "lng": 129.253693
      }
    ],
    "color": "#f16639"
  },
  {
    "path": [
      {
        "lat": 37.079266,
        "lng": 129.253693
      },
      {
        "lat": 37.079399,
        "lng": 129.252701
      }
    ],
    "color": "#4a1f9c"
  },
  {
    "path": [
      {
        "lat": 37.079399,
        "lng": 129.252701
      },
      {
        "lat": 37.079048,
        "lng": 129.25174
      }
    ],
    "color": "#8f955f"
  },
  {
    "path": [
      {
        "lat": 37.079048,
        "lng": 129.25174
      },
      {
        "lat": 37.080166,
        "lng": 129.239594
      }
    ],
    "color": "#7537df"
  },
  {
    "path": [
      {
        "lat": 37.080166,
        "lng": 129.239594
      },
      {
        "lat": 37.077415,
        "lng": 129.231766
      }
    ],
    "color": "#fbeb48"
  },
  {
    "path": [
      {
        "lat": 37.077415,
        "lng": 129.231766
      },
      {
        "lat": 37.076607,
        "lng": 129.230545
      }
    ],
    "color": "#6a8128"
  },
  {
    "path": [
      {
        "lat": 37.076607,
        "lng": 129.230545
      },
      {
        "lat": 37.076584,
        "lng": 129.230499
      }
    ],
    "color": "#e7a3cc"
  },
  {
    "path": [
      {
        "lat": 37.076584,
        "lng": 129.230499
      },
      {
        "lat": 37.076527,
        "lng": 129.230652
      }
    ],
    "color": "#af18a0"
  },
  {
    "path": [
      {
        "lat": 37.076527,
        "lng": 129.230652
      },
      {
        "lat": 37.074615,
        "lng": 129.23262
      }
    ],
    "color": "#1caf74"
  },
  {
    "path": [
      {
        "lat": 37.074615,
        "lng": 129.23262
      },
      {
        "lat": 37.073669,
        "lng": 129.235291
      }
    ],
    "color": "#4e11d5"
  },
  {
    "path": [
      {
        "lat": 37.073669,
        "lng": 129.235291
      },
      {
        "lat": 37.073509,
        "lng": 129.238739
      }
    ],
    "color": "#4c7d88"
  },
  {
    "path": [
      {
        "lat": 37.073509,
        "lng": 129.238739
      },
      {
        "lat": 37.073521,
        "lng": 129.241074
      }
    ],
    "color": "#7c802f"
  },
  {
    "path": [
      {
        "lat": 37.073521,
        "lng": 129.241074
      },
      {
        "lat": 37.073631,
        "lng": 129.241531
      }
    ],
    "color": "#7fb312"
  },
  {
    "path": [
      {
        "lat": 37.073631,
        "lng": 129.241531
      },
      {
        "lat": 37.07365,
        "lng": 129.241577
      }
    ],
    "color": "#a19cf7"
  },
  {
    "path": [
      {
        "lat": 37.07365,
        "lng": 129.241577
      },
      {
        "lat": 37.071346,
        "lng": 129.250336
      }
    ],
    "color": "#fed8c7"
  },
  {
    "path": [
      {
        "lat": 37.071346,
        "lng": 129.250336
      },
      {
        "lat": 37.072247,
        "lng": 129.251694
      }
    ],
    "color": "#569f85"
  },
  {
    "path": [
      {
        "lat": 37.072247,
        "lng": 129.251694
      },
      {
        "lat": 37.072243,
        "lng": 129.251694
      }
    ],
    "color": "#22d99d"
  },
  {
    "path": [
      {
        "lat": 37.072243,
        "lng": 129.251694
      },
      {
        "lat": 37.072296,
        "lng": 129.251755
      }
    ],
    "color": "#eb467b"
  },
  {
    "path": [
      {
        "lat": 37.072296,
        "lng": 129.251755
      },
      {
        "lat": 37.074867,
        "lng": 129.255447
      }
    ],
    "color": "#5741b5"
  },
  {
    "path": [
      {
        "lat": 37.074867,
        "lng": 129.255447
      },
      {
        "lat": 37.074963,
        "lng": 129.255539
      }
    ],
    "color": "#f3096c"
  },
  {
    "path": [
      {
        "lat": 37.074963,
        "lng": 129.255539
      },
      {
        "lat": 37.075005,
        "lng": 129.255554
      }
    ],
    "color": "#2ae4bf"
  },
  {
    "path": [
      {
        "lat": 37.075005,
        "lng": 129.255554
      },
      {
        "lat": 37.076435,
        "lng": 129.25737
      }
    ],
    "color": "#c0b30c"
  },
  {
    "path": [
      {
        "lat": 37.076435,
        "lng": 129.25737
      },
      {
        "lat": 37.078491,
        "lng": 129.260132
      }
    ],
    "color": "#24e3d4"
  },
  {
    "path": [
      {
        "lat": 37.078491,
        "lng": 129.260132
      },
      {
        "lat": 37.080795,
        "lng": 129.263931
      }
    ],
    "color": "#e9995a"
  },
  {
    "path": [
      {
        "lat": 37.080795,
        "lng": 129.263931
      },
      {
        "lat": 37.080875,
        "lng": 129.264023
      }
    ],
    "color": "#783849"
  },
  {
    "path": [
      {
        "lat": 37.080875,
        "lng": 129.264023
      },
      {
        "lat": 37.080894,
        "lng": 129.264175
      }
    ],
    "color": "#c55d46"
  },
  {
    "path": [
      {
        "lat": 37.080894,
        "lng": 129.264175
      },
      {
        "lat": 37.080372,
        "lng": 129.26709
      }
    ],
    "color": "#06685f"
  },
  {
    "path": [
      {
        "lat": 37.080372,
        "lng": 129.26709
      },
      {
        "lat": 37.080105,
        "lng": 129.269638
      }
    ],
    "color": "#4b6974"
  },
  {
    "path": [
      {
        "lat": 37.080105,
        "lng": 129.269638
      },
      {
        "lat": 37.079887,
        "lng": 129.269806
      }
    ],
    "color": "#ee3139"
  },
  {
    "path": [
      {
        "lat": 37.079887,
        "lng": 129.269806
      },
      {
        "lat": 37.079502,
        "lng": 129.27034
      }
    ],
    "color": "#31d13b"
  },
  {
    "path": [
      {
        "lat": 37.079502,
        "lng": 129.27034
      },
      {
        "lat": 37.078148,
        "lng": 129.281296
      }
    ],
    "color": "#6a0322"
  },
  {
    "path": [
      {
        "lat": 37.078148,
        "lng": 129.281296
      },
      {
        "lat": 37.078342,
        "lng": 129.281845
      }
    ],
    "color": "#d68a2d"
  },
  {
    "path": [
      {
        "lat": 37.078342,
        "lng": 129.281845
      },
      {
        "lat": 37.078323,
        "lng": 129.281754
      }
    ],
    "color": "#438147"
  },
  {
    "path": [
      {
        "lat": 37.078323,
        "lng": 129.281754
      },
      {
        "lat": 37.078312,
        "lng": 129.281647
      }
    ],
    "color": "#4c873a"
  },
  {
    "path": [
      {
        "lat": 37.078312,
        "lng": 129.281647
      },
      {
        "lat": 37.078564,
        "lng": 129.282181
      }
    ],
    "color": "#2811e0"
  },
  {
    "path": [
      {
        "lat": 37.078564,
        "lng": 129.282181
      },
      {
        "lat": 37.078556,
        "lng": 129.282516
      }
    ],
    "color": "#b4c693"
  }
]